fetcher/__init__.py
fetcher/__main__.py
fetcher/access_genbank.py
fetcher/gui.py
fetcher/user_input.py
fetcher/utils.py
fetch_features-0.2.9.dist-info/LICENSE.md
fetch_features-0.2.9.dist-info/METADATA
fetch_features-0.2.9.dist-info/WHEEL
fetch_features-0.2.9.dist-info/entry_points.txt
fetch_features-0.2.9.dist-info/top_level.txt
fetch_features-0.2.9.dist-info/RECORD
