Metadata-Version: 2.1
Name: fetch-features
Version: 0.2.9
Summary: Fetch features from a list of accession or BioSample numbers.
Author-email: Ivan Muñoz-Gutierrez <ivan.munoz.gutierrez@gmail.com>
License: BSD 3-Clause License
Project-URL: Homepage, https://github.com/ivanmugu/fetch_features
Keywords: unique identifier,accession number,BioSample number,GenBank,sequence features
Classifier: Programming Language :: Python
Classifier: License :: OSI Approved :: BSD License
Classifier: Intended Audience :: Science/Research
Classifier: Operating System :: OS Independent
Classifier: Topic :: Scientific/Engineering :: Bio-Informatics
Requires-Python: >=3.11
License-File: LICENSE.md
Requires-Dist: biopython (==1.81)
Requires-Dist: customtkinter (==5.1.3)
Requires-Dist: darkdetect (==0.8.0)
Requires-Dist: numpy (==1.24.3)
Requires-Dist: pandas (==2.0.1)
Requires-Dist: python-dateutil (==2.8.2)
Requires-Dist: pytz (==2023.3)
Requires-Dist: six (==1.16.0)
Requires-Dist: tzdata (==2023.3)
Requires-Dist: openpyxl (==3.1.2)
